odoo/addons/l10n_it_withholding_tax_mis_builder_cash_flow/README.rst
odoo/addons/l10n_it_withholding_tax_mis_builder_cash_flow/__init__.py
odoo/addons/l10n_it_withholding_tax_mis_builder_cash_flow/__manifest__.py
odoo/addons/l10n_it_withholding_tax_mis_builder_cash_flow/i18n/it.po
odoo/addons/l10n_it_withholding_tax_mis_builder_cash_flow/i18n/l10n_it_withholding_tax_mis_builder_cash_flow.pot
odoo/addons/l10n_it_withholding_tax_mis_builder_cash_flow/readme/CONTRIBUTORS.rst
odoo/addons/l10n_it_withholding_tax_mis_builder_cash_flow/readme/DESCRIPTION.rst
odoo/addons/l10n_it_withholding_tax_mis_builder_cash_flow/report/__init__.py
odoo/addons/l10n_it_withholding_tax_mis_builder_cash_flow/report/mis_cash_flow.py
odoo/addons/l10n_it_withholding_tax_mis_builder_cash_flow/report/mis_cash_flow_views.xml
odoo/addons/l10n_it_withholding_tax_mis_builder_cash_flow/static/description/icon.png
odoo/addons/l10n_it_withholding_tax_mis_builder_cash_flow/static/description/index.html
odoo/addons/l10n_it_withholding_tax_mis_builder_cash_flow/tests/__init__.py
odoo/addons/l10n_it_withholding_tax_mis_builder_cash_flow/tests/test_report.py
odoo14_addon_l10n_it_withholding_tax_mis_builder_cash_flow-14.0.1.0.1.dev3.dist-info/METADATA
odoo14_addon_l10n_it_withholding_tax_mis_builder_cash_flow-14.0.1.0.1.dev3.dist-info/WHEEL
odoo14_addon_l10n_it_withholding_tax_mis_builder_cash_flow-14.0.1.0.1.dev3.dist-info/top_level.txt
odoo14_addon_l10n_it_withholding_tax_mis_builder_cash_flow-14.0.1.0.1.dev3.dist-info/RECORD
